clickable_card/__init__.py
clickable_card/frontend/build/asset-manifest.json
clickable_card/frontend/build/bootstrap.min.css
clickable_card/frontend/build/index.html
clickable_card/frontend/build/static/js/main.0b057746.js
clickable_card/frontend/build/static/js/main.0b057746.js.LICENSE.txt
clickable_card/frontend/build/static/js/main.0b057746.js.map
clickable_card/frontend/build/static/js/main.1d0463c6.js
clickable_card/frontend/build/static/js/main.1d0463c6.js.LICENSE.txt
clickable_card/frontend/build/static/js/main.1d0463c6.js.map
clickable_card/frontend/build/static/js/main.902dd4fb.js
clickable_card/frontend/build/static/js/main.902dd4fb.js.LICENSE.txt
clickable_card/frontend/build/static/js/main.902dd4fb.js.map
clickable_card/frontend/build/static/js/main.93ea7421.js
clickable_card/frontend/build/static/js/main.93ea7421.js.LICENSE.txt
clickable_card/frontend/build/static/js/main.93ea7421.js.map
clickable_card/frontend/build/static/js/main.b379d695.js
clickable_card/frontend/build/static/js/main.b379d695.js.LICENSE.txt
clickable_card/frontend/build/static/js/main.b379d695.js.map
clickable_card/frontend/build/static/js/main.c978769c.js
clickable_card/frontend/build/static/js/main.c978769c.js.LICENSE.txt
clickable_card/frontend/build/static/js/main.c978769c.js.map
streamlit_clickable_card-1.0.0.dist-info/LICENSE
streamlit_clickable_card-1.0.0.dist-info/METADATA
streamlit_clickable_card-1.0.0.dist-info/WHEEL
streamlit_clickable_card-1.0.0.dist-info/top_level.txt
streamlit_clickable_card-1.0.0.dist-info/RECORD
