Metadata-Version: 2.1
Name: streamlit-clickable-card
Version: 1.0.0
Summary: Clickable Card
Home-page: 
Author: Hartland Brown
Author-email: hartland.brown@snowflake.com
License: UNKNOWN
Platform: UNKNOWN
Requires-Python: >=3.6
License-File: LICENSE
Requires-Dist: streamlit (>=0.63)
